pyunifi/__init__.py
pyunifi/controller.py
pyunifi-2.21.data/scripts/unifi-create-voucher
pyunifi-2.21.data/scripts/unifi-ls-clients
pyunifi-2.21.dist-info/LICENSE
pyunifi-2.21.dist-info/METADATA
pyunifi-2.21.dist-info/WHEEL
pyunifi-2.21.dist-info/top_level.txt
pyunifi-2.21.dist-info/RECORD
