Metadata-Version: 2.1
Name: pyunifi
Version: 2.21
Summary: API for Ubiquity Networks UniFi controller
Home-page: https://github.com/finish06/unifi-api
Author: Caleb Dunn
Author-email: finish.06@gmail.com
License: UNKNOWN
Platform: UNKNOWN
Requires-Dist: requests
